GPS_clock/EchoTest.py
GPS_clock/GPS_clock.HMI.py
GPS_clock/GPS_clock.tft.py
GPS_clock/__init__.py
GPS_clock/clock_v2.py
GPS_clock/dispMap.py
GPS_clock/getMap.py
GPS_clock/gpsdData.py
GPS_clock/listSats.py
GPS_clock/rawString.py
GPS_clock/simpleTest.py
GPS_clock/tftwrite.py
GPS_clock/wingsGPS.py
GPS_clock-0.1.0.dist-info/LICENSE
GPS_clock-0.1.0.dist-info/METADATA
GPS_clock-0.1.0.dist-info/WHEEL
GPS_clock-0.1.0.dist-info/top_level.txt
GPS_clock-0.1.0.dist-info/RECORD
