Metadata-Version: 2.1
Name: GPS-clock
Version: 0.1.0
Summary: A GPS clock and Nextion display tft writer
Home-page: https://www.qsl.net/zl3dw/
Author: Andrew Barron
Author-email: zl3dw@outlook.co.nz
License: UNKNOWN
Platform: UNKNOWN
Classifier: Programming Language :: Python
Classifier: Programming Language :: Python :: 3
Classifier: Programming Language :: Python :: 3.9
Requires-Python: >=3.6
License-File: LICENSE
